setup.py
tieui/__init__.py
tieui/test.py
tieui/tieui_module.py
tieui.egg-info/PKG-INFO
tieui.egg-info/SOURCES.txt
tieui.egg-info/dependency_links.txt
tieui.egg-info/requires.txt
tieui.egg-info/top_level.txt
tieui/local-version/main.js
tieui/local-version/package-lock.json
tieui/local-version/package.json
tieui/local-version/server.py
tieui/local-version/out/404.html
tieui/local-version/out/CodeInput.html
tieui/local-version/out/GeneratedUi.html
tieui/local-version/out/account.html
tieui/local-version/out/cancel.html
tieui/local-version/out/companies.html
tieui/local-version/out/contact.html
tieui/local-version/out/customers.html
tieui/local-version/out/favicon-16x16.png
tieui/local-version/out/favicon-32x32.png
tieui/local-version/out/favicon.ico
tieui/local-version/out/independent.html
tieui/local-version/out/index.html
tieui/local-version/out/live.html
tieui/local-version/out/manifest.json
tieui/local-version/out/sandbox.html
tieui/local-version/out/settings.html
tieui/local-version/out/success.html
tieui/local-version/out2/404.html
tieui/local-version/out2/CodeInput.html
tieui/local-version/out2/GeneratedUi.html
tieui/local-version/out2/account.html
tieui/local-version/out2/cancel.html
tieui/local-version/out2/companies.html
tieui/local-version/out2/contact.html
tieui/local-version/out2/customers.html
tieui/local-version/out2/favicon-16x16.png
tieui/local-version/out2/favicon-32x32.png
tieui/local-version/out2/favicon.ico
tieui/local-version/out2/independent.html
tieui/local-version/out2/index.html
tieui/local-version/out2/live.html
tieui/local-version/out2/manifest.json
tieui/local-version/out2/sandbox.html
tieui/local-version/out2/settings.html
tieui/local-version/out2/success.html
tieui/local-version/out2/_next/static/chunks/135-26f27a7875a675d4.js
tieui/local-version/out2/_next/static/chunks/138-c9d63577faf7960a.js
tieui/local-version/out2/_next/static/chunks/158-de3b2da7fc593a26.js
tieui/local-version/out2/_next/static/chunks/162-544721adb388ec7c.js
tieui/local-version/out2/_next/static/chunks/177-506216ee74187849.js
tieui/local-version/out2/_next/static/chunks/229.0bb936a67a48d471.js
