Metadata-Version: 2.1
Name: tieui
Version: 0.2.21
Summary: Tie Ui package for local development
Home-page: https://tieui.app
Author: TieUi
Author-email: info@tieUi.com
